aircall/__init__.py
aircall/client.py
aircall/exceptions.py
aircall/logging_config.py
aircall/models/__init__.py
aircall/models/ai_voice_agent.py
aircall/models/call.py
aircall/models/company.py
aircall/models/contact.py
aircall/models/content.py
aircall/models/conversation_intelligence.py
aircall/models/dialer_campaign.py
aircall/models/integration.py
aircall/models/ivr_option.py
aircall/models/message.py
aircall/models/number.py
aircall/models/participant.py
aircall/models/tag.py
aircall/models/team.py
aircall/models/user.py
aircall/models/webhook.py
aircall/resources/__init__.py
aircall/resources/base.py
aircall/resources/call.py
aircall/resources/company.py
aircall/resources/contact.py
aircall/resources/dialer_campaign.py
aircall/resources/integration.py
aircall/resources/message.py
aircall/resources/number.py
aircall/resources/tag.py
aircall/resources/team.py
aircall/resources/user.py
aircall/resources/webhook.py
aircall_api-1.2.0.dist-info/licenses/LICENSE
aircall_api-1.2.0.dist-info/METADATA
aircall_api-1.2.0.dist-info/WHEEL
aircall_api-1.2.0.dist-info/top_level.txt
aircall_api-1.2.0.dist-info/RECORD
