Metadata-Version: 2.4
Name: aircall-api
Version: 1.2.0
Summary: Python API Built to connect with aircall.io API Endpoints
License-Expression: MIT
Project-URL: Homepage, https://github.com/Riprock/aircall-api
Project-URL: Bug Tracker, https://github.com/Riprock/aircall-api/issues
Project-URL: Documentation, https://github.com/Riprock/aircall-api#readme
Project-URL: Repository, https://github.com/Riprock/aircall-api
Keywords: aircall,api,telephony,voip,phone,calls,contacts,sms,messaging,client,sdk
Requires-Python: >=3.13
License-File: LICENSE
Requires-Dist: pydantic>=2.12.4
Requires-Dist: requests>=2.32.5
Dynamic: license-file
